qubitmapping/__init__.py
qubitmapping/qubitmapping.py
qubitmapping-0.1.6.dist-info/METADATA
qubitmapping-0.1.6.dist-info/WHEEL
qubitmapping-0.1.6.dist-info/top_level.txt
qubitmapping-0.1.6.dist-info/RECORD
