Metadata-Version: 2.1
Name: qubitmapping
Version: 0.1.6
Summary: initial qubit mapping picked randomly
Author: Yongsoo Hwang
Requires-Python: >=3
